MANIFEST.in
README.rst
setup.py
jsonfinder/__init__.py
jsonfinder/__main__.py
jsonfinder.egg-info/PKG-INFO
jsonfinder.egg-info/SOURCES.txt
jsonfinder.egg-info/dependency_links.txt
jsonfinder.egg-info/entry_points.txt
jsonfinder.egg-info/pbr.json
jsonfinder.egg-info/top_level.txt
jsonfinder/tests/__init__.py
jsonfinder/tests/cli_example.txt
jsonfinder/tests/test.py
jsonfinder/tests/test.pyc
jsonfinder/tests/testin.txt
jsonfinder/tests/testout.txt