Metadata-Version: 1.1
Name: jsonfinder
Version: 0.4.2
Summary: Easily handle JSON contained within strings.
Home-page: https://github.com/alexmojaki/jsonfinder
Author: Alex Hall
Author-email: alex.mojaki@gmail.com
License: MIT
Platform: UNKNOWN
Classifier: Programming Language :: Python :: 2
Classifier: Programming Language :: Python :: 3
Classifier: Topic :: Utilities
